README.txt
setup.cfg
setup.py
docs/HISTORY.txt
docs/INSTALL.txt
docs/LICENSE.GPL
docs/LICENSE.txt
menttes/__init__.py
menttes.action.createfolder.egg-info/PKG-INFO
menttes.action.createfolder.egg-info/SOURCES.txt
menttes.action.createfolder.egg-info/dependency_links.txt
menttes.action.createfolder.egg-info/entry_points.txt
menttes.action.createfolder.egg-info/namespace_packages.txt
menttes.action.createfolder.egg-info/not-zip-safe
menttes.action.createfolder.egg-info/paster_plugins.txt
menttes.action.createfolder.egg-info/requires.txt
menttes.action.createfolder.egg-info/top_level.txt
menttes/action/__init__.py
menttes/action/createfolder/__init__.py
menttes/action/createfolder/configure.zcml
menttes/action/createfolder/createfolder.py
menttes/action/createfolder/tests.py
menttes/action/createfolder/version.txt
