Metadata-Version: 1.0
Name: menttes.action.createfolder
Version: 0.1dev-r68295
Summary: An action to create folders with content rules
Home-page: http://labs.menttes.com
Author: Roberto Allende
Author-email: rover@menttes.com
License: GPL
Keywords: content rules action create folder
Platform: UNKNOWN
Classifier: Framework :: Plone
Classifier: Framework :: Zope2
Classifier: Framework :: Zope3
Classifier: Programming Language :: Python
Classifier: Topic :: Software Development :: Libraries :: Python Modules
